{
  "schemaVersion": 1,
  "id": "dawnweapons",
  "version": "${version}",

  "name": "DawnWeapons",
  "description": "Adds new weapon stuff",
  "authors": [
    "Dawn/DawnsEdge"
  ],
  "contact": {
    "homepage": "",
    "sources": ""
  },

  "license": "CC0-1.0",
  "icon": "assets/dawnweapons/icon.png",

  "environment": "*",
  "entrypoints": {
    "main": [
      "net.dawn.dawnweapons.DawnWeapons"
    ]
  },
  "mixins": [
    "dawnweapons.mixins.json"
  ],

  "depends": {
    "fabricloader": ">=0.7.4",
    "fabric": "*",
    "minecraft": "1.16.x"
  },
  "suggests": {
    "another-mod": "*"
  }
}
